{
  "ComponentIndexes": {},
  "ControlUniqueGuids": {},
  "ControlUniqueIds": {
    "App": 1,
    "BotonGuardar": 413,
    "Button1": 50,
    "Button1_11": 86,
    "Button1_12": 91,
    "Button1_13": 87,
    "Button1_14": 298,
    "Button1_15": 92,
    "Button1_2": 190,
    "Button1_3": 37,
    "Button1_4": 296,
    "Button1_5": 303,
    "Button1_6": 260,
    "Button1_7": 259,
    "Button1_8": 99,
    "Button1_9": 100,
    "Button11_1": 96,
    "Button11_2": 193,
    "Button11_3": 40,
    "Button11_4": 289,
    "Button11_5": 254,
    "Button13": 192,
    "Button13_1": 262,
    "Button13_2": 39,
    "Button13_3": 288,
    "Button13_4": 103,
    "Button2": 208,
    "Button3": 330,
    "Button3_2": 347,
    "Button3_3": 367,
    "Button3_4": 384,
    "Button4": 189,
    "Button4_1": 36,
    "Button4_2": 295,
    "Button5": 429,
    "Button5_1": 430,
    "Button6_1": 191,
    "Button6_2": 38,
    "Button6_3": 261,
    "Button6_4": 101,
    "Button6_5": 297,
    "Button7": 250,
    "Button8": 285,
    "Button9": 379,
    "Button9_1": 340,
    "Button9_2": 361,
    "Button9_3": 396,
    "Button9_4": 343,
    "Button9_5": 358,
    "Button9_6": 365,
    "Button9_7": 376,
    "Button9_8": 393,
    "ButtonGuardar_1": 77,
    "ButtonGuardar1": 245,
    "CdigoCrystal_11": 390,
    "CdigoCrystal_13": 312,
    "CdigoCrystal_17": 313,
    "CdigoCrystal_4": 337,
    "CdigoCrystal_5": 355,
    "CdigoCrystal_6": 373,
    "CdigoCrystal9": 220,
    "CdigoMaterial": 224,
    "Checkbox4": 214,
    "Circle1": 281,
    "Circle2": 89,
    "Circle2_1": 83,
    "Codigo_rgb": 283,
    "codigoInput": 47,
    "color_Crystal": 198,
    "COLORAPP1": 188,
    "COLORAPP1_1": 35,
    "COLORAPP1_2": 10,
    "COLORAPP1_3": 294,
    "COLORAPP1_4": 258,
    "COLORAPP1_5": 98,
    "ColorCrystal": 301,
    "ColorCrystal_1": 42,
    "ColorCrystal_2": 43,
    "Colores_Crystal": 29,
    "ColoresSeleccionados": 4,
    "colorInput": 46,
    "ComboBox1": 202,
    "ComboBox1_1": 165,
    "ComboBox2": 302,
    "ComboBox2_1": 203,
    "ComboBox2_2": 180,
    "ComboBox3_1": 157,
    "ComboBox4": 406,
    "ComboBox5": 158,
    "ConAlerta44/2": 357,
    "ConAlerta78/2": 339,
    "ConAlertaElastico": 375,
    "ConAlertaLycra": 392,
    "Cont_Sugerencia_vanisados": 132,
    "Container_BarraNavegacion": 183,
    "Container_BarraNavegacion_1": 30,
    "Container_BarraNavegacion_2": 287,
    "Container_BarraNavegacionRGB": 253,
    "Container_barraNavegacionvanisados": 93,
    "Container_Botton": 249,
    "Container_codigoRGB": 264,
    "Container_Filtros": 194,
    "Container_FiltrosColorcrystal": 41,
    "Container_FiltrosVanisados": 299,
    "Container_Gallery2": 209,
    "Container_GestionVanizados": 159,
    "Container_pop_up": 231,
    "Container_Popup": 66,
    "Container1": 5,
    "Container10": 106,
    "Container11": 170,
    "Container12": 218,
    "Container13": 160,
    "Container14": 414,
    "Container15": 434,
    "Container2": 53,
    "Container22": 277,
    "Container3": 104,
    "Container4": 114,
    "Container5": 13,
    "Container6": 150,
    "Container7": 399,
    "Container8": 177,
    "Container9": 81,
    "ContainerBarratabla": 270,
    "ContainerbarratablaGallery5": 319,
    "ContainerBotones": 181,
    "ContainerBotton": 284,
    "ContainerDaToscolor_1": 386,
    "ContainerDatoscolor_2": 369,
    "ContainerDatoscolor_3": 351,
    "ContainerDatoscolor_4": 333,
    "ContaineRectangulo": 54,
    "ContainerLandingPage": 82,
    "ContainerTarjetas": 212,
    "ContenedorPopPapSugerencia": 304,
    "contenedorTarjetaElastico": 363,
    "contenedorTarjetaLycra": 381,
    "contenedortarjetaVani.44/2": 345,
    "contenedortarjetaVani.78/2": 328,
    "Datosdelcolor": 336,
    "Datosdelcolor_1": 354,
    "Datosdelcolor_2": 372,
    "Datosdelcolor_6": 389,
    "Datosdelcolor9": 222,
    "DescargarPDF": 251,
    "Descripcin": 225,
    "Dropdown1": 207,
    "Dropdown2": 201,
    "Dropdown2_1": 436,
    "DropdownColores": 49,
    "DropdownMaterial": 48,
    "Elasticoexpuesto": 324,
    "Elasticoexpuesto_1": 323,
    "Elasticoexpuesto_2": 322,
    "Elasticoexpuesto_6": 325,
    "Elasticoexpuesto_7": 321,
    "EtiquetaCodigoSAP": 74,
    "EtiquetaDescripcion": 72,
    "EtiquetaTextoCodigoSAP": 240,
    "EtiquetaTextoColorCrystal": 238,
    "EtiquetaTextoNombreColor": 236,
    "EtiquetaTextopantone": 234,
    "Gallery1": 51,
    "Gallery2": 210,
    "Gallery3": 105,
    "Gallery3_1": 11,
    "Gallery4": 115,
    "Gallery5": 133,
    "Gallery5_1": 326,
    "GalleryRGB": 275,
    "galleryTemplate1": 52,
    "galleryTemplate2": 211,
    "galleryTemplate3": 109,
    "galleryTemplate3_1": 12,
    "galleryTemplate3_2": 276,
    "galleryTemplate4": 116,
    "galleryTemplate5": 134,
    "galleryTemplate5_1": 327,
    "Host": 3,
    "Icon1": 306,
    "Icon1_1": 269,
    "Icon10": 391,
    "Icon10_1": 374,
    "Icon10_2": 356,
    "Icon10_3": 338,
    "Icon10_4": 318,
    "Icon10_5": 344,
    "Icon10_6": 362,
    "Icon10_7": 380,
    "Icon10_8": 397,
    "Icon11": 401,
    "Icon13": 155,
    "Icon15": 151,
    "Icon17": 422,
    "Icon19": 435,
    "Icon2": 266,
    "Icon2_1": 16,
    "Icon3": 230,
    "Icon4": 28,
    "Icon5": 27,
    "Icon6": 119,
    "Icon7": 59,
    "Icon8": 415,
    "Icon9": 131,
    "IconCerrarPopup": 233,
    "IconCerrarPopup_1": 68,
    "Image1": 8,
    "Image1_2": 186,
    "Image1_3": 33,
    "Image1_4": 292,
    "Image1_5": 102,
    "Image1_6": 263,
    "Image1_7": 85,
    "Image2": 7,
    "Image2_1": 187,
    "Image2_2": 34,
    "Image2_3": 293,
    "Image2_4": 316,
    "Image2_5": 257,
    "Image2_6": 97,
    "Image3": 107,
    "Image3_2": 359,
    "Image3_3": 377,
    "Image3_4": 394,
    "Image3_5": 341,
    "Image6": 152,
    "Label1": 58,
    "Label1_1": 62,
    "Label1_2": 65,
    "Label1_3": 178,
    "Label1_4": 173,
    "Label1_5": 174,
    "Label1_6": 175,
    "Label1_7": 172,
    "Label1_8": 176,
    "Label10": 90,
    "Label10_1": 84,
    "Label11": 246,
    "Label12": 79,
    "Label13": 244,
    "Label14": 153,
    "Label14_1": 154,
    "Label15": 196,
    "Label16": 418,
    "Label17": 419,
    "Label18": 423,
    "Label18_1": 424,
    "Label18_2": 425,
    "Label18_3": 426,
    "Label18_4": 427,
    "Label18_5": 428,
    "Label19": 247,
    "Label2": 9,
    "Label2_1": 268,
    "Label2_11": 22,
    "Label2_12": 23,
    "Label2_13": 24,
    "Label2_14": 25,
    "Label2_15": 26,
    "Label2_2": 273,
    "Label2_3": 274,
    "Label2_4": 267,
    "Label2_5": 272,
    "Label2_8": 15,
    "Label2_9": 21,
    "Label20": 223,
    "Label21": 248,
    "Label23": 64,
    "Label24": 78,
    "Label26": 129,
    "Label26_1": 121,
    "Label26_2": 130,
    "Label26_3": 122,
    "Label26_4": 125,
    "Label26_5": 126,
    "Label27": 118,
    "Label27_1": 127,
    "Label27_2": 128,
    "Label27_3": 120,
    "Label27_4": 123,
    "Label27_5": 124,
    "Label3": 400,
    "Label3_1": 19,
    "Label3_2": 314,
    "Label3_3": 317,
    "Label3_4": 232,
    "Label3_5": 67,
    "Label4": 342,
    "Label4_1": 20,
    "Label4_2": 360,
    "Label4_3": 378,
    "Label4_4": 395,
    "Label5": 331,
    "Label5_1": 348,
    "Label5_3": 366,
    "Label5_4": 383,
    "Label6": 185,
    "Label6_1": 32,
    "Label6_2": 291,
    "Label6_3": 95,
    "Label6_4": 88,
    "Label6_5": 256,
    "Label7": 57,
    "Label7_1": 61,
    "Label7_2": 63,
    "Label8": 402,
    "Label8_1": 73,
    "Label8_10": 410,
    "Label8_11": 411,
    "Label8_2": 404,
    "Label8_3": 407,
    "Label8_4": 409,
    "Label8_5": 69,
    "Label8_6": 403,
    "Label8_7": 71,
    "Label8_8": 405,
    "Label8_9": 408,
    "Label9": 335,
    "Label9_1": 353,
    "Label9_2": 371,
    "Label9_6": 388,
    "Label9_7": 315,
    "LabelCapturaRGB_NO_BORRAR": 217,
    "labelCoColor": 221,
    "LabelCodigoSap": 226,
    "LabelDescripcion": 227,
    "LabelNombre": 229,
    "materiaPrima": 398,
    "Materiaprimaprincipal_1": 44,
    "Materiaprimaprincipal_2": 45,
    "Materiaprimaprincipal1": 199,
    "Mssimilar1_7": 307,
    "Mssimilar1_8": 308,
    "Mssimilar4": 215,
    "Nombredecolor": 228,
    "Pantalla_GestionVanisados": 80,
    "Pantalla_Pantone": 182,
    "Pantalla_RGB_ENEAS": 252,
    "Pantalla_Vanisados": 286,
    "Pantonecdigo": 200,
    "Pantonecdigo_1": 197,
    "RecomendadoTextinput": 412,
    "Rectangle1_2": 94,
    "Rectangle10": 117,
    "Rectangle10_1": 161,
    "Rectangle10_2": 163,
    "Rectangle10_3": 164,
    "Rectangle10_4": 162,
    "Rectangle11": 184,
    "Rectangle11_1": 255,
    "Rectangle11_2": 6,
    "Rectangle11_3": 31,
    "Rectangle11_4": 290,
    "Rectangle15": 329,
    "Rectangle15_1": 56,
    "Rectangle15_2": 60,
    "Rectangle15_5": 305,
    "Rectangle151": 213,
    "Rectangle16": 332,
    "Rectangle16_3": 310,
    "Rectangle161": 216,
    "Rectangle18": 219,
    "Rectangle2": 309,
    "Rectangle211": 195,
    "Rectangle211_1": 179,
    "Rectangle3": 271,
    "Rectangle4": 55,
    "Rectangle40": 320,
    "Rectangle5": 300,
    "Rectangle6": 279,
    "Rectangle6_1": 14,
    "Rectangle6_2": 280,
    "Rectangle7": 171,
    "Rectangle7_1": 17,
    "Rectangle73": 334,
    "Rectangle73_3": 311,
    "Rectangle8_1": 18,
    "Rectangle86": 346,
    "Rectangle86_2": 364,
    "Rectangle86_4": 382,
    "Rectangle87": 350,
    "Rectangle87_2": 368,
    "Rectangle87_4": 385,
    "Rectangle89": 352,
    "Rectangle89_2": 370,
    "Rectangle89_4": 387,
    "ReporteRGBcolorCrystal": 76,
    "Separator2_1": 278,
    "Subtitle1": 108,
    "Subtitle3_1": 416,
    "Subtitle3_2": 417,
    "Subtitle3_3": 420,
    "Subtitle3_4": 421,
    "TextInput1": 166,
    "TextInput1_1": 265,
    "TextInput1_2": 167,
    "TextInput1_3": 168,
    "TextInput1_4": 169,
    "TextInputB": 206,
    "TextInputG": 205,
    "TextInputR": 204,
    "TextInputReporteRGB1": 243,
    "TextInputSearchUser": 156,
    "TextoEtiquetaCodigocolor_1": 70,
    "TextoEtiquetaCodigoSAP": 241,
    "TextoEtiquetacolorCrystal": 239,
    "TextoEtiquetaNomColor": 237,
    "TextoEtiquetaPantone": 235,
    "TextoEtiquetaReporte": 242,
    "TextoEtiquetaReporte_1": 75,
    "Title2_2": 282,
    "Vector11": 349
  },
  "FunctionParamsInvariantScripts": {},
  "FunctionParamsInvariantScriptsOnInstances": {},
  "HeaderLastSavedDateTimeUTC": "09/12/2023 19:08:00",
  "IsLegacyComponentAllowGlobalScopeCase": false,
  "LocalConnectionIDReferences": {
    "1978edba-129a-4788-ac84-95c33de78f45": "\"/providers/microsoft.powerapps/apis/shared_sharepointonline/connections/39a961530ca847eeb644439f144820a3\"",
    "328686de-30ee-4626-8c09-41ce6413aff1": "\"/providers/microsoft.powerapps/apis/shared_logicflows/connections/0080976a07634f6da51ea9bc2870ef45\"",
    "5397bef3-3a93-4303-b144-6bd2d3016aae": "\"/providers/microsoft.powerapps/apis/shared_office365users/connections/526e141ad6f74bf2bee749f19f6553d3\"",
    "55239ff6-3b7d-493c-9ff0-7e94cfce4e3c": "\"/providers/microsoft.powerapps/apis/shared_logicflows/connections/c7fa322d60c146f9b2ec7941dead6609\"",
    "59da2bca-7b26-43fc-b553-e0a9d66ff507": "\"/providers/microsoft.powerapps/apis/shared_logicflows/connections/31798efe83c84b41965bd4fa41fa2ba4\"",
    "7df666c6-7d79-4d58-b33b-d82d977c2d79": "\"/providers/microsoft.powerapps/apis/shared_logicflows/connections/219e980a7bec4f3998e073d85566a53c\"",
    "9a24fbdc-798f-486f-b584-e62af4cd2856": "\"/providers/microsoft.powerapps/apis/shared_logicflows/connections/6c73d51f3f9a466d91e3bec1f67bb252\"",
    "a7ec6d9a-d534-4de6-849b-1393ad1fbcb1": "\"/providers/microsoft.powerapps/apis/shared_powerappsforappmakers/connections/3a3091476bbf48f7a76461550ce1da31\"",
    "b6965406-cef4-4463-b637-dee95013238d": "\"/providers/microsoft.powerapps/apis/shared_office365/connections/d748b939655646ffac5af3dd44f18f80\"",
    "c9ba4016-d7f7-4e05-a65f-cf99d7651151": "\"/providers/microsoft.powerapps/apis/shared_logicflows/connections/06751798cf0946088d84d2d584bbd88d\"",
    "e5946533-6f62-4dd4-84c0-ff6b1a0cb43e": "\"/providers/microsoft.powerapps/apis/shared_powerappsforappmakers/connections/3a3091476bbf48f7a76461550ce1da31\""
  },
  "LocalDatabaseReferencesAsEmpty": false,
  "LocalResourceFileNames": {
    "alert-circle": "0001.png",
    "image13189": "0002.png",
    "image13191": "0003.png",
    "image13193": "0004.png",
    "image13214": "0005.png",
    "image13215": "0006.png",
    "image13216": "0007.png",
    "intercambiar": "0010.png",
    "intercambiar (1)": "0008.png",
    "intercambiar (2)": "0009.png",
    "MicrosoftTeams-image (1)": "0011.png",
    "MicrosoftTeams-image (2)": "0012.png",
    "MicrosoftTeams-image (4)": "0013.png",
    "VAyR": "0014.gif",
    "Vector": "0020.png",
    "Vector (1)": "0015.png",
    "Vector (2)": "0016.png",
    "Vector (3)": "0017.png",
    "Vector (4)": "0018.png",
    "Vector (5)": "0019.png"
  },
  "LocalResourceRootPaths": {
    "alert-circle": "https://docserverpwaprodwus.blob.core.windows.net/59498fee-8d2a-43c3-8291-28a087f1e149-1/resource/Assets0Images00001.png?sv=2018-03-28&sr=b&sig=E%2Bk7ZkwjVKyMqx9RD1R1h1FRXa4oKWCEj9p%2BY%2Fe5b4U%3D&spr=https&se=2023-09-13T18%3A40%3A28Z&sp=r",
    "image13189": "https://docserverpwaprodwus.blob.core.windows.net/59498fee-8d2a-43c3-8291-28a087f1e149-1/resource/Assets0Images00002.png?sv=2018-03-28&sr=b&sig=QpiTmn39xFKwICV1AOJJEFmPabCxFTVQwrzhPS0CMHI%3D&spr=https&se=2023-09-13T18%3A40%3A28Z&sp=r",
    "image13191": "https://docserverpwaprodwus.blob.core.windows.net/59498fee-8d2a-43c3-8291-28a087f1e149-1/resource/Assets0Images00003.png?sv=2018-03-28&sr=b&sig=A9mVzNsZ9q%2FYMnuzFOtIu5kt9wt%2BpgQiUfJSKZa7Vtk%3D&spr=https&se=2023-09-13T18%3A40%3A28Z&sp=r",
    "image13193": "https://docserverpwaprodwus.blob.core.windows.net/59498fee-8d2a-43c3-8291-28a087f1e149-1/resource/Assets0Images00004.png?sv=2018-03-28&sr=b&sig=%2F%2Frwu6ZYCowcM2TNQ8dRW1162AyqK3ip%2BFwUFePqAZE%3D&spr=https&se=2023-09-13T18%3A40%3A28Z&sp=r",
    "image13214": "https://docserverpwaprodwus.blob.core.windows.net/59498fee-8d2a-43c3-8291-28a087f1e149-1/resource/Assets0Images00005.png?sv=2018-03-28&sr=b&sig=iUiOZ6SRQkQhPqd6S3yVRAlA45CDStTfCmPo6j2JhKk%3D&spr=https&se=2023-09-13T18%3A40%3A28Z&sp=r",
    "image13215": "https://docserverpwaprodwus.blob.core.windows.net/59498fee-8d2a-43c3-8291-28a087f1e149-1/resource/Assets0Images00006.png?sv=2018-03-28&sr=b&sig=6uMZRaWMaYoKEm46PhaDZRW%2F5Od944DE3FV7RCa8fug%3D&spr=https&se=2023-09-13T18%3A40%3A28Z&sp=r",
    "image13216": "https://docserverpwaprodwus.blob.core.windows.net/59498fee-8d2a-43c3-8291-28a087f1e149-1/resource/Assets0Images00007.png?sv=2018-03-28&sr=b&sig=aYrSETZTB0oZNJFN56dzbQoLRgHoKoPgfwdFaN7lTe8%3D&spr=https&se=2023-09-13T18%3A40%3A28Z&sp=r",
    "intercambiar": "https://docserverpwaprodwus.blob.core.windows.net/59498fee-8d2a-43c3-8291-28a087f1e149-1/resource/Assets0Images00010.png?sv=2018-03-28&sr=b&sig=QxqrOxBU%2F6qyAN5ZCNkD2eTrpUAAjwadu3ob5ivLoAI%3D&spr=https&se=2023-09-13T18%3A40%3A28Z&sp=r",
    "intercambiar (1)": "https://docserverpwaprodwus.blob.core.windows.net/59498fee-8d2a-43c3-8291-28a087f1e149-1/resource/Assets0Images00008.png?sv=2018-03-28&sr=b&sig=GOy04W5ndK2D%2BY7twDhHTVD5I9kzj6urwVyoTX%2BBTRg%3D&spr=https&se=2023-09-13T18%3A40%3A28Z&sp=r",
    "intercambiar (2)": "https://docserverpwaprodwus.blob.core.windows.net/59498fee-8d2a-43c3-8291-28a087f1e149-1/resource/Assets0Images00009.png?sv=2018-03-28&sr=b&sig=MyLqk%2BOlKyk081AE75WyShSrJGKPsfxZdk%2F5aiDP7Ag%3D&spr=https&se=2023-09-13T18%3A40%3A28Z&sp=r",
    "MicrosoftTeams-image (1)": "https://docserverpwaprodwus.blob.core.windows.net/59498fee-8d2a-43c3-8291-28a087f1e149-1/resource/Assets0Images00011.png?sv=2018-03-28&sr=b&sig=zUqmVoXXtyuj5ZjeNpLgccpFew6vXKry1XGwzrZ39jo%3D&spr=https&se=2023-09-13T18%3A40%3A28Z&sp=r",
    "MicrosoftTeams-image (2)": "https://docserverpwaprodwus.blob.core.windows.net/59498fee-8d2a-43c3-8291-28a087f1e149-1/resource/Assets0Images00012.png?sv=2018-03-28&sr=b&sig=T%2BdaPcSHxSDZSORwdMRocgD9fNmLk%2FqKCxmUknls7OI%3D&spr=https&se=2023-09-13T18%3A40%3A28Z&sp=r",
    "MicrosoftTeams-image (4)": "https://docserverpwaprodwus.blob.core.windows.net/59498fee-8d2a-43c3-8291-28a087f1e149-1/resource/Assets0Images00013.png?sv=2018-03-28&sr=b&sig=9HTIt188FDsLc5at8mTG9XL2xVr6jvQ3C7RG8STX9Hg%3D&spr=https&se=2023-09-13T18%3A40%3A28Z&sp=r",
    "VAyR": "https://docserverpwaprodwus.blob.core.windows.net/59498fee-8d2a-43c3-8291-28a087f1e149-1/resource/Assets0Images00014.gif?sv=2018-03-28&sr=b&sig=oI87OkrxpW7Ushs4YBhEUruq1zvTRZJ8mAqQzrHjA9w%3D&spr=https&se=2023-09-13T18%3A40%3A28Z&sp=r",
    "Vector": "https://docserverpwaprodwus.blob.core.windows.net/59498fee-8d2a-43c3-8291-28a087f1e149-1/resource/Assets0Images00020.png?sv=2018-03-28&sr=b&sig=KNYpFgXO0xNlqEcHvPwot95%2FJY0VemTmLiu45YqlZNg%3D&spr=https&se=2023-09-13T18%3A40%3A28Z&sp=r",
    "Vector (1)": "https://docserverpwaprodwus.blob.core.windows.net/59498fee-8d2a-43c3-8291-28a087f1e149-1/resource/Assets0Images00015.png?sv=2018-03-28&sr=b&sig=yugRsqubr%2Fqfa0HtafQcU0vFRZ5Fp0VMZW0e5f91LfA%3D&spr=https&se=2023-09-13T18%3A40%3A28Z&sp=r",
    "Vector (2)": "https://docserverpwaprodwus.blob.core.windows.net/59498fee-8d2a-43c3-8291-28a087f1e149-1/resource/Assets0Images00016.png?sv=2018-03-28&sr=b&sig=BY%2FBsSTk1y%2Bt5uk%2BDajS6Sx%2FSCg4mXsI453FHOI4mg4%3D&spr=https&se=2023-09-13T18%3A40%3A28Z&sp=r",
    "Vector (3)": "https://docserverpwaprodwus.blob.core.windows.net/59498fee-8d2a-43c3-8291-28a087f1e149-1/resource/Assets0Images00017.png?sv=2018-03-28&sr=b&sig=T49v0K7atOKpb1ZPaQWMrazyH2qkwRb%2Bi7564P0M0Yk%3D&spr=https&se=2023-09-13T18%3A40%3A28Z&sp=r",
    "Vector (4)": "https://docserverpwaprodwus.blob.core.windows.net/59498fee-8d2a-43c3-8291-28a087f1e149-1/resource/Assets0Images00018.png?sv=2018-03-28&sr=b&sig=Hu5%2FfIYTerbV5pieVTXXYU3zKS%2B%2BkEhFJxReHwxHz08%3D&spr=https&se=2023-09-13T18%3A40%3A28Z&sp=r",
    "Vector (5)": "https://docserverpwaprodwus.blob.core.windows.net/59498fee-8d2a-43c3-8291-28a087f1e149-1/resource/Assets0Images00019.png?sv=2018-03-28&sr=b&sig=U6h85XeJYbvftLJpUNut%2BqYhmEvPbXRa1sn6CgpKm7Y%3D&spr=https&se=2023-09-13T18%3A40%3A28Z&sp=r"
  },
  "OldLogoFileName": "logo.jpg",
  "OrderComponentMetadata": {},
  "OrderComponentTemplate": {},
  "OrderDataSource": {
    "adminUsers": 19,
    "afColorCalceteria": 0,
    "afColorCalceteriaDev": 1,
    "afExcelEneas": 2,
    "afVanizadosUnico": 3,
    "coleccionAlternativa": 20,
    "colorCalceteriaDev": 7,
    "coloresUnicosDev": 8,
    "Colorrgb": 21,
    "ComboBoxSample": 9,
    "CustomGallerySample": 10,
    "DatosUsoColorApp": 11,
    "DropDownSample": 12,
    "gall": 22,
    "gallVanisadoUnico": 23,
    "GestionVanisadosDEV": 13,
    "ListboxSample": 14,
    "MyCollection": 24,
    "obtener_usuarios_color_app": 4,
    "Office365Outlook": 5,
    "pantoneRgbFull_1Dev": 15,
    "ReporteDeErrores": 16,
    "Roles": 17,
    "SugerenciaVanisados": 18,
    "usersGall": 25,
    "UsuariosdeOffice365": 6
  },
  "OrderGroupControls": {},
  "OrderPcfTemplate": {},
  "OrderTemplate": {},
  "OrderXMLTemplate": {
    "button": 6,
    "checkbox": 11,
    "circle": 9,
    "combobox": 10,
    "dropdown": 8,
    "gallery": 4,
    "groupContainer": 0,
    "icon": 5,
    "image": 2,
    "label": 3,
    "rectangle": 1,
    "text": 7
  },
  "OverridablePropertiesEntry": {
    "App": {},
    "BotonGuardar": {},
    "Button1": {},
    "Button1_11": {},
    "Button1_12": {},
    "Button1_13": {},
    "Button1_14": {},
    "Button1_15": {},
    "Button1_2": {},
    "Button1_3": {},
    "Button1_4": {},
    "Button1_5": {},
    "Button1_6": {},
    "Button1_7": {},
    "Button1_8": {},
    "Button1_9": {},
    "Button11_1": {},
    "Button11_2": {},
    "Button11_3": {},
    "Button11_4": {},
    "Button11_5": {},
    "Button13": {},
    "Button13_1": {},
    "Button13_2": {},
    "Button13_3": {},
    "Button13_4": {},
    "Button2": {},
    "Button3": {},
    "Button3_2": {},
    "Button3_3": {},
    "Button3_4": {},
    "Button4": {},
    "Button4_1": {},
    "Button4_2": {},
    "Button5": {},
    "Button5_1": {},
    "Button6_1": {},
    "Button6_2": {},
    "Button6_3": {},
    "Button6_4": {},
    "Button6_5": {},
    "Button7": {},
    "Button8": {},
    "Button9": {},
    "Button9_1": {},
    "Button9_2": {},
    "Button9_3": {},
    "Button9_4": {},
    "Button9_5": {},
    "Button9_6": {},
    "Button9_7": {},
    "Button9_8": {},
    "ButtonGuardar_1": {},
    "ButtonGuardar1": {},
    "CdigoCrystal_11": {},
    "CdigoCrystal_13": {},
    "CdigoCrystal_17": {},
    "CdigoCrystal_4": {},
    "CdigoCrystal_5": {},
    "CdigoCrystal_6": {},
    "CdigoCrystal9": {},
    "CdigoMaterial": {},
    "Checkbox4": {},
    "Circle1": {},
    "Circle2": {},
    "Circle2_1": {},
    "Codigo_rgb": {},
    "codigoInput": {},
    "color_Crystal": {},
    "COLORAPP1": {},
    "COLORAPP1_1": {},
    "COLORAPP1_2": {},
    "COLORAPP1_3": {},
    "COLORAPP1_4": {},
    "COLORAPP1_5": {},
    "ColorCrystal": {},
    "ColorCrystal_1": {},
    "ColorCrystal_2": {},
    "Colores_Crystal": {},
    "ColoresSeleccionados": {},
    "colorInput": {},
    "ComboBox1": {},
    "ComboBox1_1": {},
    "ComboBox2": {},
    "ComboBox2_1": {},
    "ComboBox2_2": {},
    "ComboBox3_1": {},
    "ComboBox4": {},
    "ComboBox5": {},
    "ConAlerta44/2": {},
    "ConAlerta78/2": {},
    "ConAlertaElastico": {},
    "ConAlertaLycra": {},
    "Cont_Sugerencia_vanisados": {},
    "Container_BarraNavegacion": {},
    "Container_BarraNavegacion_1": {},
    "Container_BarraNavegacion_2": {},
    "Container_BarraNavegacionRGB": {},
    "Container_barraNavegacionvanisados": {},
    "Container_Botton": {},
    "Container_codigoRGB": {},
    "Container_Filtros": {},
    "Container_FiltrosColorcrystal": {},
    "Container_FiltrosVanisados": {},
    "Container_Gallery2": {},
    "Container_GestionVanizados": {},
    "Container_pop_up": {},
    "Container_Popup": {},
    "Container1": {},
    "Container10": {},
    "Container11": {},
    "Container12": {},
    "Container13": {},
    "Container14": {},
    "Container15": {},
    "Container2": {},
    "Container22": {},
    "Container3": {},
    "Container4": {},
    "Container5": {},
    "Container6": {},
    "Container7": {},
    "Container8": {},
    "Container9": {},
    "ContainerBarratabla": {},
    "ContainerbarratablaGallery5": {},
    "ContainerBotones": {},
    "ContainerBotton": {},
    "ContainerDaToscolor_1": {},
    "ContainerDatoscolor_2": {},
    "ContainerDatoscolor_3": {},
    "ContainerDatoscolor_4": {},
    "ContaineRectangulo": {},
    "ContainerLandingPage": {},
    "ContainerTarjetas": {},
    "ContenedorPopPapSugerencia": {},
    "contenedorTarjetaElastico": {},
    "contenedorTarjetaLycra": {},
    "contenedortarjetaVani.44/2": {},
    "contenedortarjetaVani.78/2": {},
    "Datosdelcolor": {},
    "Datosdelcolor_1": {},
    "Datosdelcolor_2": {},
    "Datosdelcolor_6": {},
    "Datosdelcolor9": {},
    "DescargarPDF": {},
    "Descripcin": {},
    "Dropdown1": {},
    "Dropdown2": {},
    "Dropdown2_1": {},
    "DropdownColores": {},
    "DropdownMaterial": {},
    "Elasticoexpuesto": {},
    "Elasticoexpuesto_1": {},
    "Elasticoexpuesto_2": {},
    "Elasticoexpuesto_6": {},
    "Elasticoexpuesto_7": {},
    "EtiquetaCodigoSAP": {},
    "EtiquetaDescripcion": {},
    "EtiquetaTextoCodigoSAP": {},
    "EtiquetaTextoColorCrystal": {},
    "EtiquetaTextoNombreColor": {},
    "EtiquetaTextopantone": {},
    "Gallery1": {},
    "Gallery2": {},
    "Gallery3": {},
    "Gallery3_1": {},
    "Gallery4": {},
    "Gallery5": {},
    "Gallery5_1": {},
    "GalleryRGB": {},
    "galleryTemplate1": {},
    "galleryTemplate2": {},
    "galleryTemplate3": {},
    "galleryTemplate3_1": {},
    "galleryTemplate3_2": {},
    "galleryTemplate4": {},
    "galleryTemplate5": {},
    "galleryTemplate5_1": {},
    "Host": {},
    "Icon1": {},
    "Icon1_1": {},
    "Icon10": {},
    "Icon10_1": {},
    "Icon10_2": {},
    "Icon10_3": {},
    "Icon10_4": {},
    "Icon10_5": {},
    "Icon10_6": {},
    "Icon10_7": {},
    "Icon10_8": {},
    "Icon11": {},
    "Icon13": {},
    "Icon15": {},
    "Icon17": {},
    "Icon19": {},
    "Icon2": {},
    "Icon2_1": {},
    "Icon3": {},
    "Icon4": {},
    "Icon5": {},
    "Icon6": {},
    "Icon7": {},
    "Icon8": {},
    "Icon9": {},
    "IconCerrarPopup": {},
    "IconCerrarPopup_1": {},
    "Image1": {},
    "Image1_2": {},
    "Image1_3": {},
    "Image1_4": {},
    "Image1_5": {},
    "Image1_6": {},
    "Image1_7": {},
    "Image2": {},
    "Image2_1": {},
    "Image2_2": {},
    "Image2_3": {},
    "Image2_4": {},
    "Image2_5": {},
    "Image2_6": {},
    "Image3": {},
    "Image3_2": {},
    "Image3_3": {},
    "Image3_4": {},
    "Image3_5": {},
    "Image6": {},
    "Label1": {},
    "Label1_1": {},
    "Label1_2": {},
    "Label1_3": {},
    "Label1_4": {},
    "Label1_5": {},
    "Label1_6": {},
    "Label1_7": {},
    "Label1_8": {},
    "Label10": {},
    "Label10_1": {},
    "Label11": {},
    "Label12": {},
    "Label13": {},
    "Label14": {},
    "Label14_1": {},
    "Label15": {},
    "Label16": {},
    "Label17": {},
    "Label18": {},
    "Label18_1": {},
    "Label18_2": {},
    "Label18_3": {},
    "Label18_4": {},
    "Label18_5": {},
    "Label19": {},
    "Label2": {},
    "Label2_1": {},
    "Label2_11": {},
    "Label2_12": {},
    "Label2_13": {},
    "Label2_14": {},
    "Label2_15": {},
    "Label2_2": {},
    "Label2_3": {},
    "Label2_4": {},
    "Label2_5": {},
    "Label2_8": {},
    "Label2_9": {},
    "Label20": {},
    "Label21": {},
    "Label23": {},
    "Label24": {},
    "Label26": {},
    "Label26_1": {},
    "Label26_2": {},
    "Label26_3": {},
    "Label26_4": {},
    "Label26_5": {},
    "Label27": {},
    "Label27_1": {},
    "Label27_2": {},
    "Label27_3": {},
    "Label27_4": {},
    "Label27_5": {},
    "Label3": {},
    "Label3_1": {},
    "Label3_2": {},
    "Label3_3": {},
    "Label3_4": {},
    "Label3_5": {},
    "Label4": {},
    "Label4_1": {},
    "Label4_2": {},
    "Label4_3": {},
    "Label4_4": {},
    "Label5": {},
    "Label5_1": {},
    "Label5_3": {},
    "Label5_4": {},
    "Label6": {},
    "Label6_1": {},
    "Label6_2": {},
    "Label6_3": {},
    "Label6_4": {},
    "Label6_5": {},
    "Label7": {},
    "Label7_1": {},
    "Label7_2": {},
    "Label8": {},
    "Label8_1": {},
    "Label8_10": {},
    "Label8_11": {},
    "Label8_2": {},
    "Label8_3": {},
    "Label8_4": {},
    "Label8_5": {},
    "Label8_6": {},
    "Label8_7": {},
    "Label8_8": {},
    "Label8_9": {},
    "Label9": {},
    "Label9_1": {},
    "Label9_2": {},
    "Label9_6": {},
    "Label9_7": {},
    "LabelCapturaRGB_NO_BORRAR": {},
    "labelCoColor": {},
    "LabelCodigoSap": {},
    "LabelDescripcion": {},
    "LabelNombre": {},
    "materiaPrima": {},
    "Materiaprimaprincipal_1": {},
    "Materiaprimaprincipal_2": {},
    "Materiaprimaprincipal1": {},
    "Mssimilar1_7": {},
    "Mssimilar1_8": {},
    "Mssimilar4": {},
    "Nombredecolor": {},
    "Pantalla_GestionVanisados": {},
    "Pantalla_Pantone": {},
    "Pantalla_RGB_ENEAS": {},
    "Pantalla_Vanisados": {},
    "Pantonecdigo": {},
    "Pantonecdigo_1": {},
    "RecomendadoTextinput": {},
    "Rectangle1_2": {},
    "Rectangle10": {},
    "Rectangle10_1": {},
    "Rectangle10_2": {},
    "Rectangle10_3": {},
    "Rectangle10_4": {},
    "Rectangle11": {},
    "Rectangle11_1": {},
    "Rectangle11_2": {},
    "Rectangle11_3": {},
    "Rectangle11_4": {},
    "Rectangle15": {},
    "Rectangle15_1": {},
    "Rectangle15_2": {},
    "Rectangle15_5": {},
    "Rectangle151": {},
    "Rectangle16": {},
    "Rectangle16_3": {},
    "Rectangle161": {},
    "Rectangle18": {},
    "Rectangle2": {},
    "Rectangle211": {},
    "Rectangle211_1": {},
    "Rectangle3": {},
    "Rectangle4": {},
    "Rectangle40": {},
    "Rectangle5": {},
    "Rectangle6": {},
    "Rectangle6_1": {},
    "Rectangle6_2": {},
    "Rectangle7": {},
    "Rectangle7_1": {},
    "Rectangle73": {},
    "Rectangle73_3": {},
    "Rectangle8_1": {},
    "Rectangle86": {},
    "Rectangle86_2": {},
    "Rectangle86_4": {},
    "Rectangle87": {},
    "Rectangle87_2": {},
    "Rectangle87_4": {},
    "Rectangle89": {},
    "Rectangle89_2": {},
    "Rectangle89_4": {},
    "ReporteRGBcolorCrystal": {},
    "Separator2_1": {},
    "Subtitle1": {},
    "Subtitle3_1": {},
    "Subtitle3_2": {},
    "Subtitle3_3": {},
    "Subtitle3_4": {},
    "TextInput1": {},
    "TextInput1_1": {},
    "TextInput1_2": {},
    "TextInput1_3": {},
    "TextInput1_4": {},
    "TextInputB": {},
    "TextInputG": {},
    "TextInputR": {},
    "TextInputReporteRGB1": {},
    "TextInputSearchUser": {},
    "TextoEtiquetaCodigocolor_1": {},
    "TextoEtiquetaCodigoSAP": {},
    "TextoEtiquetacolorCrystal": {},
    "TextoEtiquetaNomColor": {},
    "TextoEtiquetaPantone": {},
    "TextoEtiquetaReporte": {},
    "TextoEtiquetaReporte_1": {},
    "Title2_2": {},
    "Vector11": {}
  },
  "PCFDynamicSchemaForIRRetrievalEntry": {},
  "PCFTemplateEntry": {},
  "PublishOrderIndices": {
    "App": 0,
    "BotonGuardar": 412,
    "Button1": 51,
    "Button1_11": 91,
    "Button1_12": 96,
    "Button1_13": 92,
    "Button1_14": 302,
    "Button1_15": 97,
    "Button1_2": 192,
    "Button1_3": 39,
    "Button1_4": 300,
    "Button1_5": 306,
    "Button1_6": 263,
    "Button1_7": 262,
    "Button1_8": 103,
    "Button1_9": 104,
    "Button11_1": 100,
    "Button11_2": 195,
    "Button11_3": 42,
    "Button11_4": 293,
    "Button11_5": 257,
    "Button13": 194,
    "Button13_1": 265,
    "Button13_2": 41,
    "Button13_3": 292,
    "Button13_4": 107,
    "Button2": 209,
    "Button3": 338,
    "Button3_2": 353,
    "Button3_3": 371,
    "Button3_4": 386,
    "Button4": 191,
    "Button4_1": 38,
    "Button4_2": 299,
    "Button5": 0,
    "Button5_1": 0,
    "Button6_1": 193,
    "Button6_2": 40,
    "Button6_3": 264,
    "Button6_4": 105,
    "Button6_5": 301,
    "Button7": 249,
    "Button8": 284,
    "Button9": 382,
    "Button9_1": 347,
    "Button9_2": 366,
    "Button9_3": 397,
    "Button9_4": 350,
    "Button9_5": 363,
    "Button9_6": 369,
    "Button9_7": 379,
    "Button9_8": 394,
    "ButtonGuardar_1": 76,
    "ButtonGuardar1": 245,
    "CdigoCrystal_11": 389,
    "CdigoCrystal_13": 314,
    "CdigoCrystal_17": 315,
    "CdigoCrystal_4": 342,
    "CdigoCrystal_5": 358,
    "CdigoCrystal_6": 374,
    "CdigoCrystal9": 230,
    "CdigoMaterial": 222,
    "Checkbox4": 215,
    "Circle1": 281,
    "Circle2": 94,
    "Circle2_1": 88,
    "Codigo_rgb": 283,
    "codigoInput": 48,
    "color_Crystal": 199,
    "COLORAPP1": 190,
    "COLORAPP1_1": 37,
    "COLORAPP1_2": 11,
    "COLORAPP1_3": 298,
    "COLORAPP1_4": 261,
    "COLORAPP1_5": 102,
    "ColorCrystal": 304,
    "ColorCrystal_1": 43,
    "ColorCrystal_2": 44,
    "Colores_Crystal": 28,
    "ColoresSeleccionados": 3,
    "colorInput": 47,
    "ComboBox1": 203,
    "ComboBox1_1": 167,
    "ComboBox2": 305,
    "ComboBox2_1": 204,
    "ComboBox2_2": 180,
    "ComboBox3_1": 157,
    "ComboBox4": 405,
    "ComboBox5": 158,
    "ConAlerta44/2": 331,
    "ConAlerta78/2": 329,
    "ConAlertaElastico": 333,
    "ConAlertaLycra": 335,
    "Cont_Sugerencia_vanisados": 84,
    "Container_BarraNavegacion": 182,
    "Container_BarraNavegacion_1": 29,
    "Container_BarraNavegacion_2": 286,
    "Container_BarraNavegacionRGB": 252,
    "Container_barraNavegacionvanisados": 81,
    "Container_Botton": 185,
    "Container_codigoRGB": 253,
    "Container_Filtros": 183,
    "Container_FiltrosColorcrystal": 30,
    "Container_FiltrosVanisados": 287,
    "Container_Gallery2": 184,
    "Container_GestionVanizados": 86,
    "Container_pop_up": 211,
    "Container_Popup": 32,
    "Container1": 4,
    "Container10": 110,
    "Container11": 160,
    "Container12": 219,
    "Container13": 159,
    "Container14": 0,
    "Container15": 0,
    "Container2": 53,
    "Container22": 277,
    "Container3": 82,
    "Container4": 83,
    "Container5": 14,
    "Container6": 85,
    "Container7": 291,
    "Container8": 161,
    "Container9": 80,
    "ContainerBarratabla": 254,
    "ContainerbarratablaGallery5": 289,
    "ContainerBotones": 162,
    "ContainerBotton": 256,
    "ContainerDaToscolor_1": 388,
    "ContainerDatoscolor_2": 373,
    "ContainerDatoscolor_3": 357,
    "ContainerDatoscolor_4": 341,
    "ContaineRectangulo": 54,
    "ContainerLandingPage": 87,
    "ContainerTarjetas": 213,
    "ContenedorPopPapSugerencia": 288,
    "contenedorTarjetaElastico": 332,
    "contenedorTarjetaLycra": 334,
    "contenedortarjetaVani.44/2": 330,
    "contenedortarjetaVani.78/2": 328,
    "Datosdelcolor": 346,
    "Datosdelcolor_1": 362,
    "Datosdelcolor_2": 378,
    "Datosdelcolor_6": 393,
    "Datosdelcolor9": 220,
    "DescargarPDF": 250,
    "Descripcin": 223,
    "Dropdown1": 208,
    "Dropdown2": 202,
    "Dropdown2_1": 112,
    "DropdownColores": 50,
    "DropdownMaterial": 49,
    "Elasticoexpuesto": 325,
    "Elasticoexpuesto_1": 324,
    "Elasticoexpuesto_2": 323,
    "Elasticoexpuesto_6": 326,
    "Elasticoexpuesto_7": 322,
    "EtiquetaCodigoSAP": 73,
    "EtiquetaDescripcion": 71,
    "EtiquetaTextoCodigoSAP": 240,
    "EtiquetaTextoColorCrystal": 238,
    "EtiquetaTextoNombreColor": 236,
    "EtiquetaTextopantone": 234,
    "Gallery1": 31,
    "Gallery2": 210,
    "Gallery3": 108,
    "Gallery3_1": 12,
    "Gallery4": 117,
    "Gallery5": 134,
    "Gallery5_1": 290,
    "GalleryRGB": 255,
    "galleryTemplate1": 52,
    "galleryTemplate2": 212,
    "galleryTemplate3": 111,
    "galleryTemplate3_1": 13,
    "galleryTemplate3_2": 276,
    "galleryTemplate4": 119,
    "galleryTemplate5": 136,
    "galleryTemplate5_1": 327,
    "Host": 0,
    "Icon1": 308,
    "Icon1_1": 271,
    "Icon10": 390,
    "Icon10_1": 375,
    "Icon10_2": 359,
    "Icon10_3": 343,
    "Icon10_4": 320,
    "Icon10_5": 351,
    "Icon10_6": 367,
    "Icon10_7": 383,
    "Icon10_8": 398,
    "Icon11": 400,
    "Icon13": 155,
    "Icon15": 151,
    "Icon17": 143,
    "Icon19": 114,
    "Icon2": 268,
    "Icon2_1": 17,
    "Icon3": 228,
    "Icon4": 6,
    "Icon5": 5,
    "Icon6": 122,
    "Icon7": 58,
    "Icon8": 144,
    "Icon9": 118,
    "IconCerrarPopup": 233,
    "IconCerrarPopup_1": 67,
    "Image1": 9,
    "Image1_2": 188,
    "Image1_3": 35,
    "Image1_4": 296,
    "Image1_5": 106,
    "Image1_6": 266,
    "Image1_7": 90,
    "Image2": 8,
    "Image2_1": 189,
    "Image2_2": 36,
    "Image2_3": 297,
    "Image2_4": 318,
    "Image2_5": 260,
    "Image2_6": 101,
    "Image3": 115,
    "Image3_2": 364,
    "Image3_3": 380,
    "Image3_4": 395,
    "Image3_5": 348,
    "Image6": 152,
    "Label1": 57,
    "Label1_1": 61,
    "Label1_2": 64,
    "Label1_3": 178,
    "Label1_4": 174,
    "Label1_5": 175,
    "Label1_6": 176,
    "Label1_7": 173,
    "Label1_8": 177,
    "Label10": 95,
    "Label10_1": 89,
    "Label11": 246,
    "Label12": 78,
    "Label13": 244,
    "Label14": 153,
    "Label14_1": 154,
    "Label15": 197,
    "Label16": 146,
    "Label17": 145,
    "Label18": 137,
    "Label18_1": 138,
    "Label18_2": 139,
    "Label18_3": 140,
    "Label18_4": 141,
    "Label18_5": 142,
    "Label19": 247,
    "Label2": 10,
    "Label2_1": 270,
    "Label2_11": 23,
    "Label2_12": 24,
    "Label2_13": 25,
    "Label2_14": 26,
    "Label2_15": 27,
    "Label2_2": 274,
    "Label2_3": 275,
    "Label2_4": 269,
    "Label2_5": 273,
    "Label2_8": 16,
    "Label2_9": 22,
    "Label20": 221,
    "Label21": 248,
    "Label23": 63,
    "Label24": 77,
    "Label26": 132,
    "Label26_1": 124,
    "Label26_2": 133,
    "Label26_3": 125,
    "Label26_4": 128,
    "Label26_5": 129,
    "Label27": 121,
    "Label27_1": 130,
    "Label27_2": 131,
    "Label27_3": 123,
    "Label27_4": 126,
    "Label27_5": 127,
    "Label3": 399,
    "Label3_1": 20,
    "Label3_2": 316,
    "Label3_3": 319,
    "Label3_4": 232,
    "Label3_5": 66,
    "Label4": 349,
    "Label4_1": 21,
    "Label4_2": 365,
    "Label4_3": 381,
    "Label4_4": 396,
    "Label5": 339,
    "Label5_1": 354,
    "Label5_3": 370,
    "Label5_4": 385,
    "Label6": 187,
    "Label6_1": 34,
    "Label6_2": 295,
    "Label6_3": 99,
    "Label6_4": 93,
    "Label6_5": 259,
    "Label7": 56,
    "Label7_1": 60,
    "Label7_2": 62,
    "Label8": 401,
    "Label8_1": 72,
    "Label8_10": 409,
    "Label8_11": 410,
    "Label8_2": 403,
    "Label8_3": 406,
    "Label8_4": 408,
    "Label8_5": 68,
    "Label8_6": 402,
    "Label8_7": 70,
    "Label8_8": 404,
    "Label8_9": 407,
    "Label9": 345,
    "Label9_1": 361,
    "Label9_2": 377,
    "Label9_6": 392,
    "Label9_7": 317,
    "LabelCapturaRGB_NO_BORRAR": 218,
    "labelCoColor": 231,
    "LabelCodigoSap": 224,
    "LabelDescripcion": 225,
    "LabelNombre": 227,
    "materiaPrima": 336,
    "Materiaprimaprincipal_1": 45,
    "Materiaprimaprincipal_2": 46,
    "Materiaprimaprincipal1": 200,
    "Mssimilar1_7": 309,
    "Mssimilar1_8": 310,
    "Mssimilar4": 216,
    "Nombredecolor": 226,
    "Pantalla_GestionVanisados": 79,
    "Pantalla_Pantone": 181,
    "Pantalla_RGB_ENEAS": 251,
    "Pantalla_Vanisados": 285,
    "Pantonecdigo": 201,
    "Pantonecdigo_1": 198,
    "RecomendadoTextinput": 411,
    "Rectangle1_2": 98,
    "Rectangle10": 120,
    "Rectangle10_1": 163,
    "Rectangle10_2": 165,
    "Rectangle10_3": 166,
    "Rectangle10_4": 164,
    "Rectangle11": 186,
    "Rectangle11_1": 258,
    "Rectangle11_2": 7,
    "Rectangle11_3": 33,
    "Rectangle11_4": 294,
    "Rectangle15": 337,
    "Rectangle15_1": 55,
    "Rectangle15_2": 59,
    "Rectangle15_5": 307,
    "Rectangle151": 214,
    "Rectangle16": 340,
    "Rectangle16_3": 312,
    "Rectangle161": 217,
    "Rectangle18": 229,
    "Rectangle2": 311,
    "Rectangle211": 196,
    "Rectangle211_1": 179,
    "Rectangle3": 272,
    "Rectangle4": 65,
    "Rectangle40": 321,
    "Rectangle5": 303,
    "Rectangle6": 279,
    "Rectangle6_1": 15,
    "Rectangle6_2": 280,
    "Rectangle7": 172,
    "Rectangle7_1": 18,
    "Rectangle73": 344,
    "Rectangle73_3": 313,
    "Rectangle8_1": 19,
    "Rectangle86": 352,
    "Rectangle86_2": 368,
    "Rectangle86_4": 384,
    "Rectangle87": 356,
    "Rectangle87_2": 372,
    "Rectangle87_4": 387,
    "Rectangle89": 360,
    "Rectangle89_2": 376,
    "Rectangle89_4": 391,
    "ReporteRGBcolorCrystal": 75,
    "Separator2_1": 278,
    "Subtitle1": 116,
    "Subtitle3_1": 147,
    "Subtitle3_2": 148,
    "Subtitle3_3": 149,
    "Subtitle3_4": 150,
    "TextInput1": 168,
    "TextInput1_1": 267,
    "TextInput1_2": 169,
    "TextInput1_3": 170,
    "TextInput1_4": 171,
    "TextInputB": 207,
    "TextInputG": 206,
    "TextInputR": 205,
    "TextInputReporteRGB1": 243,
    "TextInputSearchUser": 156,
    "TextoEtiquetaCodigocolor_1": 69,
    "TextoEtiquetaCodigoSAP": 241,
    "TextoEtiquetacolorCrystal": 239,
    "TextoEtiquetaNomColor": 237,
    "TextoEtiquetaPantone": 235,
    "TextoEtiquetaReporte": 242,
    "TextoEtiquetaReporte_1": 74,
    "Title2_2": 282,
    "Vector11": 355
  },
  "ResourcesJsonIndices": {
    "Image-alert-circle": 1,
    "Image-image13189": 2,
    "Image-image13191": 3,
    "Image-image13193": 4,
    "Image-image13214": 5,
    "Image-image13215": 6,
    "Image-image13216": 7,
    "Image-intercambiar": 10,
    "Image-intercambiar (1)": 8,
    "Image-intercambiar (2)": 9,
    "Image-MicrosoftTeams-image (1)": 11,
    "Image-MicrosoftTeams-image (2)": 12,
    "Image-MicrosoftTeams-image (4)": 13,
    "Image-SampleImage": 0,
    "Image-VAyR": 14,
    "Image-Vector": 20,
    "Image-Vector (1)": 15,
    "Image-Vector (2)": 16,
    "Image-Vector (3)": 17,
    "Image-Vector (4)": 18,
    "Image-Vector (5)": 19
  },
  "RuleScreenIdWithoutScreen": {},
  "TemplateVersions": {},
  "VolatileProperties": {
    "AnalysisLoadTime": 2.5360652,
    "ControlCount": {
      "button": 52,
      "checkbox": 1,
      "circle": 3,
      "combobox": 8,
      "dropdown": 6,
      "gallery": 8,
      "galleryTemplate": 8,
      "groupContainer": 52,
      "icon": 32,
      "image": 21,
      "label": 173,
      "rectangle": 46,
      "screen": 6,
      "text": 14
    },
    "DeserializationLoadTime": 3.6497124
  },
  "WasLocalDatabaseReferencesEmpty": true
}